jinja2_ospath/__init__.py
jinja2_ospath/extensions.py
jinja2_ospath-0.3.0.dist-info/METADATA
jinja2_ospath-0.3.0.dist-info/RECORD
jinja2_ospath-0.3.0.dist-info/WHEEL
jinja2_ospath-0.3.0.dist-info/top_level.txt
