Metadata-Version: 2.1
Name: jinja2-ospath
Version: 0.3.0
Summary: A Jinja2 extension that introduces the template filters basename and dirname.
Home-page: https://github.com/Midnighter/jinja2_ospath
Author: Moritz Emanuel Beber
Author-email: midnighter@posteo.net
License: 3-Clause BSD License
Keywords: jinja2 extension os.path dirname basename
Platform: UNKNOWN
Classifier: Development Status :: 2 - Pre-Alpha
Classifier: Intended Audience :: Developers
Classifier: License :: OSI Approved :: BSD License
Classifier: Natural Language :: English
Classifier: Programming Language :: Python :: 2
Classifier: Programming Language :: Python :: 2.7
Classifier: Programming Language :: Python :: 3
Classifier: Programming Language :: Python :: 3.4
Classifier: Programming Language :: Python :: 3.5
Classifier: Programming Language :: Python :: 3.6
Requires-Dist: jinja2
